<?xml version="1.0" encoding="utf-8"?>
<Document>
  <Engineering version="V19" />
  <SW.Blocks.InstanceDB ID="0">
    <AttributeList>
      <InstanceOfName>Lubr_Pump</InstanceOfName>
      <InstanceOfType>FB</InstanceOfType>
      <Interface><Sections xmlns="http://www.siemens.com/automation/Openness/SW/Interface/v5">
  <Section Name="Input">
    <Member Name="DataIn" Datatype="Struct">
      <Member Name="SensorLevel" Datatype="Bool" />
    </Member>
    <Member Name="ValveCycleTimeOut" Datatype="Time" />
    <Member Name="Simulation" Datatype="Bool" />
  </Section>
  <Section Name="Output">
    <Member Name="ValveCmd" Datatype="Bool" />
  </Section>
  <Section Name="InOut">
    <Member Name="Par" Datatype="&quot;LubrPump_Par&quot;" />
  </Section>
  <Section Name="Static">
    <Member Name="Ctrl" Datatype="Struct">
      <Member Name="RunReq" Datatype="Bool" />
    </Member>
    <Member Name="Sts" Datatype="Struct">
      <Member Name="OldValve" Datatype="Int" />
    </Member>
    <Member Name="Alarm" Datatype="&quot;LubrPump_Alr&quot;" />
    <Member Name="HMI" Datatype="&quot;LubrMotorPump_HMI&quot;" />
    <Member Name="LubrInterface" Datatype="&quot;LubrValve_ITF&quot;" />
    <Member Name="tonLowLevel" Datatype="IEC_TIMER" Version="1.0" />
    <Member Name="tonValveON" Datatype="IEC_TIMER" Version="1.0" />
    <Member Name="tonValveOFF" Datatype="IEC_TIMER" Version="1.0" />
    <Member Name="ValveChianTimeOut" Datatype="IEC_TIMER" Version="1.0" />
  </Section>
</Sections></Interface>
      <Name>CarriageLub_Pump</Name>
      <Namespace />
      <Number>130</Number>
      <ProgrammingLanguage>DB</ProgrammingLanguage>
    </AttributeList>
    <ObjectList>
      <MultilingualText ID="1" CompositionName="Comment">
        <ObjectList>
          <MultilingualTextItem ID="2" CompositionName="Items">
            <AttributeList>
              <Culture>en-US</Culture>
              <Text />
            </AttributeList>
          </MultilingualTextItem>
          <MultilingualTextItem ID="3" CompositionName="Items">
            <AttributeList>
              <Culture>en-GB</Culture>
              <Text />
            </AttributeList>
          </MultilingualTextItem>
          <MultilingualTextItem ID="4" CompositionName="Items">
            <AttributeList>
              <Culture>it-IT</Culture>
              <Text />
            </AttributeList>
          </MultilingualTextItem>
        </ObjectList>
      </MultilingualText>
      <MultilingualText ID="5" CompositionName="Title">
        <ObjectList>
          <MultilingualTextItem ID="6" CompositionName="Items">
            <AttributeList>
              <Culture>en-US</Culture>
              <Text />
            </AttributeList>
          </MultilingualTextItem>
          <MultilingualTextItem ID="7" CompositionName="Items">
            <AttributeList>
              <Culture>en-GB</Culture>
              <Text />
            </AttributeList>
          </MultilingualTextItem>
          <MultilingualTextItem ID="8" CompositionName="Items">
            <AttributeList>
              <Culture>it-IT</Culture>
              <Text />
            </AttributeList>
          </MultilingualTextItem>
        </ObjectList>
      </MultilingualText>
    </ObjectList>
  </SW.Blocks.InstanceDB>
</Document>