<?xml version="1.0" encoding="utf-8"?>
<Document>
  <Engineering version="V19" />
  <SW.Types.PlcStruct ID="0">
    <AttributeList>
      <Access>Published</Access>
      <Interface><Sections xmlns="http://www.siemens.com/automation/Openness/SW/Interface/v5">
  <Section Name="None">
    <Member Name="AutReady" Datatype="Bool">
      <Comment>
        <MultiLanguageText Lang="it-IT">Lower Dead Point</MultiLanguageText>
        <MultiLanguageText Lang="en-GB">Lower Dead Point</MultiLanguageText>
        <MultiLanguageText Lang="en-US">Machine ready for automatic cycle</MultiLanguageText>
      </Comment>
    </Member>
    <Member Name="Aborting" Datatype="Bool">
      <Comment>
        <MultiLanguageText Lang="it-IT">Machine must stay in Normal Stop During Restart</MultiLanguageText>
        <MultiLanguageText Lang="en-GB">Machine must stay in Normal Stop During Restart</MultiLanguageText>
        <MultiLanguageText Lang="en-US">Machine is aborting (alarm presence)</MultiLanguageText>
      </Comment>
    </Member>
    <Member Name="AckStopInPhase" Datatype="Bool">
      <Comment>
        <MultiLanguageText Lang="it-IT">Stop cycle for aborting</MultiLanguageText>
        <MultiLanguageText Lang="en-GB">Stop cycle for aborting</MultiLanguageText>
        <MultiLanguageText Lang="en-US">Machine ack to area stop in phase</MultiLanguageText>
      </Comment>
    </Member>
    <Member Name="AckStopProgrammed" Datatype="Bool">
      <Comment>
        <MultiLanguageText Lang="it-IT">Stop cycle programmed has been done</MultiLanguageText>
        <MultiLanguageText Lang="en-GB">Stop cycle programmed has been done</MultiLanguageText>
        <MultiLanguageText Lang="en-US">Machine ack to area stop programmed</MultiLanguageText>
      </Comment>
    </Member>
    <Member Name="MotionsStandStill" Datatype="Bool">
      <Comment>
        <MultiLanguageText Lang="it-IT">Alarms Synch sensor (table) not catch / loose</MultiLanguageText>
        <MultiLanguageText Lang="en-GB">Alarms Synch sensor (table) not catch / loose</MultiLanguageText>
        <MultiLanguageText Lang="en-US">Machine motion Standstill</MultiLanguageText>
      </Comment>
    </Member>
    <Member Name="AlarmsPresence" Datatype="Bool">
      <Comment>
        <MultiLanguageText Lang="it-IT">Alarms &amp; Mesage Out</MultiLanguageText>
        <MultiLanguageText Lang="en-GB">Alarms &amp; Mesage Out</MultiLanguageText>
        <MultiLanguageText Lang="en-US">Machine alarms presence (for lamp signaling)</MultiLanguageText>
      </Comment>
    </Member>
    <Member Name="WarningPresence" Datatype="Bool">
      <Comment>
        <MultiLanguageText Lang="it-IT">Warnings</MultiLanguageText>
        <MultiLanguageText Lang="en-GB">Warnings</MultiLanguageText>
        <MultiLanguageText Lang="en-US">Machine warnings presence (for lamp signaling)</MultiLanguageText>
      </Comment>
    </Member>
  </Section>
</Sections></Interface>
      <Name>MachineInterface</Name>
      <Namespace />
    </AttributeList>
    <ObjectList>
      <MultilingualText ID="1" CompositionName="Comment">
        <ObjectList>
          <MultilingualTextItem ID="2" CompositionName="Items">
            <AttributeList>
              <Culture>en-US</Culture>
              <Text />
            </AttributeList>
          </MultilingualTextItem>
          <MultilingualTextItem ID="3" CompositionName="Items">
            <AttributeList>
              <Culture>en-GB</Culture>
              <Text />
            </AttributeList>
          </MultilingualTextItem>
          <MultilingualTextItem ID="4" CompositionName="Items">
            <AttributeList>
              <Culture>it-IT</Culture>
              <Text />
            </AttributeList>
          </MultilingualTextItem>
        </ObjectList>
      </MultilingualText>
      <MultilingualText ID="5" CompositionName="Title">
        <ObjectList>
          <MultilingualTextItem ID="6" CompositionName="Items">
            <AttributeList>
              <Culture>en-US</Culture>
              <Text />
            </AttributeList>
          </MultilingualTextItem>
          <MultilingualTextItem ID="7" CompositionName="Items">
            <AttributeList>
              <Culture>en-GB</Culture>
              <Text />
            </AttributeList>
          </MultilingualTextItem>
          <MultilingualTextItem ID="8" CompositionName="Items">
            <AttributeList>
              <Culture>it-IT</Culture>
              <Text />
            </AttributeList>
          </MultilingualTextItem>
        </ObjectList>
      </MultilingualText>
    </ObjectList>
  </SW.Types.PlcStruct>
</Document>